irobotcreate/__init__.py
irobotcreate/drive_util.py
irobotcreate/raw_test_create_v1.py
irobotcreate/raw_test_create_v2.py
irobotcreate/roomba.py
irobotcreate/sensor_groups.py
irobotcreate/sensor_packets.py
irobotcreate-2.1.dist-info/METADATA
irobotcreate-2.1.dist-info/WHEEL
irobotcreate-2.1.dist-info/top_level.txt
irobotcreate-2.1.dist-info/RECORD
